pytoughreact/__init__.py
pytoughreact/py.typed
pytoughreact/version.py
pytoughreact/chemical/__init__.py
pytoughreact/chemical/bio_process_description.py
pytoughreact/chemical/biomass_composition.py
pytoughreact/chemical/chemical_composition.py
pytoughreact/chemical/kinetic_properties.py
pytoughreact/chemical/mineral_composition.py
pytoughreact/chemical/mineral_description.py
pytoughreact/chemical/mineral_zone.py
pytoughreact/chemical/perm_poro_zone.py
pytoughreact/constants/__init__.py
pytoughreact/constants/cap_pressure_constants.py
pytoughreact/constants/default_minerals.py
pytoughreact/constants/defaults_constants.py
pytoughreact/constants/format_specifications.py
pytoughreact/constants/generalconstants.py
pytoughreact/constants/grid_constants.py
pytoughreact/constants/plotconstants.py
pytoughreact/constants/reactionconstants.py
pytoughreact/constants/rel_perm_constants.py
pytoughreact/constants/sections.py
pytoughreact/exceptions/__init__.py
pytoughreact/exceptions/custom_error.py
pytoughreact/plotting/__init__.py
pytoughreact/plotting/plot_multiple.py
pytoughreact/plotting/plot_multiple_files_routine.py
pytoughreact/plotting/plot_multiple_tough_routine.py
pytoughreact/plotting/plot_single.py
pytoughreact/plotting/plot_tough_routine.py
pytoughreact/results/__init__.py
pytoughreact/results/multi_result_tough_3.py
pytoughreact/results/multi_result_tough_react.py
pytoughreact/results/result_multiple.py
pytoughreact/results/result_single.py
pytoughreact/results/result_tough_3.py
pytoughreact/results/result_tough_react.py
pytoughreact/results/simple_experiment_data.py
pytoughreact/results/t2result.py
pytoughreact/utilities/__init__.py
pytoughreact/utilities/t2_tough_react_utilities.py
pytoughreact/utilities/t2_utilities.py
pytoughreact/wrapper/__init__.py
pytoughreact/wrapper/react_data.py
pytoughreact/wrapper/reactblock.py
pytoughreact/wrapper/reactgrid.py
pytoughreact/wrapper/reactzone.py
pytoughreact/writers/__init__.py
pytoughreact/writers/bio_writing.py
pytoughreact-1.0.4.dist-info/LICENSE
pytoughreact-1.0.4.dist-info/METADATA
pytoughreact-1.0.4.dist-info/WHEEL
pytoughreact-1.0.4.dist-info/top_level.txt
pytoughreact-1.0.4.dist-info/RECORD
