Metadata-Version: 2.1
Name: pytoughreact
Version: 1.0.4
Summary: Python Library for automating reaction simulations using TOUGHREACT, TMVOC and TMVOC-BIO
Author-email: Temitope Ajayi <ajayi_temmy@yahoo.com>
Maintainer-email: Temitope Ajayi <ajayi_temmy@yahoo.com>
License: MIT License
Project-URL: repository, https://github.com/temmy222/PyTOUGHREACT
Keywords: biodegradation,reactive transport,automation,uncertainty quantification
Classifier: Programming Language :: Python :: 2
Classifier: Programming Language :: Python :: 3
Classifier: Programming Language :: Python :: 3.7
Classifier: Programming Language :: Python :: 3.8
Classifier: Programming Language :: Python :: 3.9
Classifier: Programming Language :: Python :: 3.10
Classifier: Programming Language :: Python :: 3.11
Classifier: License :: OSI Approved :: MIT License
Classifier: Operating System :: OS Independent
Requires-Python: >=3.7
License-File: LICENSE
Requires-Dist: numpy >=1
Requires-Dist: scipy >=1
Requires-Dist: vtk >=1
Requires-Dist: matplotlib >=3
Requires-Dist: pandas >=1
Requires-Dist: PyTOUGH
Requires-Dist: flake8
